cloudsync/__init__.py
cloudsync/__main__.py
cloudsync/cs.py
cloudsync/event.py
cloudsync/exceptions.py
cloudsync/hierarchical_cache.py
cloudsync/log.py
cloudsync/long_poll.py
cloudsync/notification.py
cloudsync/provider.py
cloudsync/py.typed
cloudsync/registry.py
cloudsync/runnable.py
cloudsync/smartsync.py
cloudsync/types.py
cloudsync/utils.py
cloudsync/command/__init__.py
cloudsync/command/debug.py
cloudsync/command/list.py
cloudsync/command/main.py
cloudsync/command/sync.py
cloudsync/command/utils.py
cloudsync/oauth/__init__.py
cloudsync/oauth/apiserver.py
cloudsync/oauth/oauth_config.py
cloudsync/oauth/redir_server.py
cloudsync/providers/__init__.py
cloudsync/providers/box.py
cloudsync/providers/dropbox.py
cloudsync/providers/filesystem.py
cloudsync/providers/mock.py
cloudsync/sync/__init__.py
cloudsync/sync/manager.py
cloudsync/sync/sqlite_storage.py
cloudsync/sync/state.py
cloudsync/tests/__init__.py
cloudsync/tests/conftest.py
cloudsync/tests/pytest.ini
cloudsync/tests/sync_notification_handler.py
cloudsync/tests/test_box.py
cloudsync/tests/test_cmd_debug.py
cloudsync/tests/test_cmd_list.py
cloudsync/tests/test_cmd_main.py
cloudsync/tests/test_cmd_sync.py
cloudsync/tests/test_cs.py
cloudsync/tests/test_dropbox.py
cloudsync/tests/test_events.py
cloudsync/tests/test_fs_provider.py
cloudsync/tests/test_hierarchical_cache.py
cloudsync/tests/test_longpoll.py
cloudsync/tests/test_notification.py
cloudsync/tests/test_oauth.py
cloudsync/tests/test_oauth_redir_server.py
cloudsync/tests/test_prov_unit.py
cloudsync/tests/test_provider.py
cloudsync/tests/test_registry.py
cloudsync/tests/test_resolve_file.py
cloudsync/tests/test_runnable.py
cloudsync/tests/test_state.py
cloudsync/tests/test_storage.py
cloudsync/tests/test_sync.py
cloudsync/tests/test_utils.py
cloudsync/tests/fixtures/__init__.py
cloudsync/tests/fixtures/fake_api.py
cloudsync/tests/fixtures/mock_provider.py
cloudsync/tests/fixtures/mock_storage.py
cloudsync/tests/fixtures/util.py
cloudsync-3.4.0.dist-info/entry_points.txt
cloudsync-3.4.0.dist-info/LICENSE
cloudsync-3.4.0.dist-info/WHEEL
cloudsync-3.4.0.dist-info/METADATA
cloudsync-3.4.0.dist-info/RECORD
