Metadata-Version: 2.1
Name: cloudsync
Version: 3.4.0
Summary: cloudsync enables simple cloud file-level sync with a variety of cloud providers
Home-page: https://github.com/atakamallc/cloudsync
Author: Atakama, LLC
Author-email: dev-support@atakama.com
Requires-Python: >=3.6
Classifier: Intended Audience :: Developers
Classifier: License :: OSI Approved :: GNU Lesser General Public License v3 or later (LGPLv3+)
Classifier: Programming Language :: Python
Classifier: Topic :: Software Development :: Libraries :: Python Modules
Requires-Dist: arrow~=0.17.0
Requires-Dist: dataclasses; python_version < '3.7'
Requires-Dist: pystrict
Requires-Dist: msgpack
Requires-Dist: requests_oauthlib
Requires-Dist: python-daemon
Requires-Dist: xxhash
Requires-Dist: urllib3>=1.25.3
Requires-Dist: watchdog
Requires-Dist: pywin32; sys_platform == 'win32'
Requires-Dist: cloudsync-gdrive>=2.0.0 ; extra == "all"
Requires-Dist: cloudsync-onedrive>=3.1.9 ; extra == "all"
Requires-Dist: boxsdk[jwt] ; extra == "all"
Requires-Dist: dropbox>=10.3.0 ; extra == "all"
Requires-Dist: six>=1.14.0 ; extra == "all"
Requires-Dist: boxsdk>=2.9.0 ; extra == "all"
Requires-Dist: boxsdk>=2.9.0 ; extra == "box"
Requires-Dist: boxsdk[jwt] ; extra == "boxcom"
Requires-Dist: dropbox>=10.3.0 ; extra == "dropbox"
Requires-Dist: six>=1.14.0 ; extra == "dropbox"
Requires-Dist: cloudsync-gdrive>=2.0.0 ; extra == "gdrive"
Requires-Dist: cloudsync-onedrive>=3.1.9 ; extra == "onedrive"
Provides-Extra: all
Provides-Extra: box
Provides-Extra: boxcom
Provides-Extra: dropbox
Provides-Extra: gdrive
Provides-Extra: onedrive
